clouddl/__init__.py
clouddl/clouddl.py
clouddl-0.5.0.dist-info/METADATA
clouddl-0.5.0.dist-info/WHEEL
clouddl-0.5.0.dist-info/licenses/LICENSE
clouddl-0.5.0.dist-info/RECORD
