Metadata-Version: 2.1
Name: clouddl
Version: 0.5.0
Summary: Python library that allows you to parse Google Drive & Dropbox links and download files
Project-URL: Homepage, https://github.com/duckduckgrayduck/clouddl
Project-URL: Bug Tracker, https://github.com/duckduckgrayduck/clouddl/issues
Author-email: duckduckgrayduck <sanjin+clouddl@muckrock.com>
License-File: LICENSE
Classifier: License :: OSI Approved :: MIT License
Classifier: Operating System :: OS Independent
Classifier: Programming Language :: Python :: 3
Requires-Python: >=3.7
Requires-Dist: bs4
Requires-Dist: googledrivedl
Requires-Dist: patool
Requires-Dist: requests
